bayesianbandits/__init__.py
bayesianbandits/_arm.py
bayesianbandits/_arm_featurizer.py
bayesianbandits/_estimators.py
bayesianbandits/_gaussian.py
bayesianbandits/_np_utils.py
bayesianbandits/_sparse_bayesian_linear_regression.py
bayesianbandits/api.py
bayesianbandits/featurizers/__init__.py
bayesianbandits/featurizers/_arm_column.py
bayesianbandits/featurizers/_function.py
bayesianbandits/pipelines/__init__.py
bayesianbandits/pipelines/_agent.py
bayesianbandits/pipelines/_learner.py
bayesianbandits/policies/__init__.py
bayesianbandits/policies/_base.py
bayesianbandits/policies/_epsilon_greedy.py
bayesianbandits/policies/_exp3a.py
bayesianbandits/policies/_thompson_sampling.py
bayesianbandits/policies/_upper_confidence_bound.py
bayesianbandits-1.2.0.dist-info/METADATA
bayesianbandits-1.2.0.dist-info/WHEEL
bayesianbandits-1.2.0.dist-info/licenses/LICENSE
bayesianbandits-1.2.0.dist-info/RECORD
