Metadata-Version: 2.4
Name: bayesianbandits
Version: 1.2.0
Summary: A Pythonic microframework for Multi-Armed Bandit algorithms.
Author-email: Rishi Kulkarni <rishi@kulkarni.science>
License-File: LICENSE
Requires-Python: >=3.10
Requires-Dist: attrs>=21.2.0
Requires-Dist: numpy>=1.23.5
Requires-Dist: scikit-learn>=1.5.2
Requires-Dist: scipy>=1.14.0
Requires-Dist: typing-extensions>=4.8.0
